.gitignore
MANIFEST.in
README.md
README.rst
setup.py
sliders/__init__.py
sliders/flextableparser.py
sliders/text2table.py
sliders.egg-info/PKG-INFO
sliders.egg-info/SOURCES.txt
sliders.egg-info/dependency_links.txt
sliders.egg-info/entry_points.txt
sliders.egg-info/not-zip-safe
sliders.egg-info/top_level.txt
sliders/table_schemas/fastqc.json
sliders/table_schemas/flagstat.json
sliders/table_schemas/rtg_vcfstats.json
sliders/table_schemas/vcflib_vcfhethom.json
sliders/table_schemas/vcflib_vcfstats.json
sliders/tests/__init__.py
sliders/tests/fastqc.csv
sliders/tests/sample_fastqc.data
sliders/tests/sample_fastqc_2.data
sliders/tests/sample_flagstat.tsv
sliders/tests/test_fastqc.csv
sliders/tests/test_flextableparser.py
sliders/tests/test_static_fastqc.csv
sliders/tests/test_text2table.py