Metadata-Version: 1.1
Name: sliders
Version: 0.2.0
Summary: Refactor and reformat text data
Home-page: http://github.com/stanfordbioinformatics/sliders
Author: Paul Billing-Ross
Author-email: pbilling@stanford.edu
License: MIT
Keywords: text table csv refactor reformat convert
Platform: UNKNOWN
Classifier: License :: OSI Approved :: MIT License
Classifier: Programming Language :: Python :: 2
Classifier: Programming Language :: Python :: 2.7
Classifier: Programming Language :: Python :: 3
